aiohttp_isal/__init__.py
aiohttp_isal/py.typed
aiohttp_isal-0.3.2.dist-info/LICENSE
aiohttp_isal-0.3.2.dist-info/METADATA
aiohttp_isal-0.3.2.dist-info/WHEEL
aiohttp_isal-0.3.2.dist-info/RECORD
