Metadata-Version: 2.1
Name: aiohttp-isal
Version: 0.3.2
Summary: isal support for aiohttp
Home-page: https://github.com/bdraco/aiohttp-isal
Author: J. Nick Koston
Author-email: nick@koston.org
Requires-Python: >=3.8,<4.0
Classifier: Development Status :: 2 - Pre-Alpha
Classifier: Intended Audience :: Developers
Classifier: License :: OSI Approved :: Apache Software License
Classifier: Natural Language :: English
Classifier: Operating System :: OS Independent
Classifier: Programming Language :: Python :: 3
Classifier: Programming Language :: Python :: 3.8
Classifier: Programming Language :: Python :: 3.9
Classifier: Programming Language :: Python :: 3.10
Classifier: Programming Language :: Python :: 3.11
Classifier: Programming Language :: Python :: 3.12
Classifier: Topic :: Software Development :: Libraries
Requires-Dist: aiohttp (>=3.9.0)
Requires-Dist: isal (>=1.6.1) ; sys_platform == "darwin"
Requires-Dist: isal (>=1.6.1) ; sys_platform == "linux"
Requires-Dist: isal (>=1.6.1) ; sys_platform == "win32"
Project-URL: Bug Tracker, https://github.com/bdraco/aiohttp-isal/issues
Project-URL: Changelog, https://github.com/bdraco/aiohttp-isal/blob/main/CHANGELOG.md
Project-URL: Documentation, https://aiohttp-isal.readthedocs.io
Project-URL: Repository, https://github.com/bdraco/aiohttp-isal
